django_useful_things/__init__.py
django_useful_things/admin.py
django_useful_things/apps.py
django_useful_things/models.py
django_useful_things/signals.py
django_useful_things/tests.py
django_useful_things/urls.py
django_useful_things/views.py
django_useful_things/migrations/__init__.py
django_useful_things-1.0.0.dist-info/METADATA
django_useful_things-1.0.0.dist-info/RECORD
django_useful_things-1.0.0.dist-info/WHEEL
django_useful_things-1.0.0.dist-info/top_level.txt
